[{
	"id": 0,
	"language": "actionscript3.as"
}, {
	"id": 1,
	"language": "applescript.scpt"
}, {
	"id": 2,
	"language": "assembler_intel.asm"
}, {
	"id": 3,
	"language": "clisp.lisp"
}, {
	"id": 4,
	"language": "clojure.clj"
}, {
	"id": 5,
	"language": "dart.dart"
}, {
	"id": 6,
	"language": "delphi.delphi"
}, {
	"id": 7,
	"language": "erlang_hw.erl"
}, {
	"id": 8,
	"language": "go.go"
}, {
	"id": 9,
	"language": "groovy.groovy"
}, {
	"id": 10,
	"language": "jade.jade"
}, {
	"id": 11,
	"language": "linux-x86.nasm"
}, {
	"id": 12,
	"language": "lisp.lsp"
}, {
	"id": 13,
	"language": "morsecode"
}, {
	"id": 14,
	"language": "objc.m"
}, {
	"id": 15,
	"language": "perl.pl"
}, {
	"id": 16,
	"language": "postscript.ps"
}, {
	"id": 17,
	"language": "R.R"
}, {
	"id": 18,
	"language": "rust.rs"
}, {
	"id": 19,
	"language": "scala.scala"
}, {
	"id": 20,
	"language": "swift.swift"
}, {
	"id": 21,
	"language": "tcl.tcl"
}, {
	"id": 22,
	"language": "tk.tk"
}]